spirofs/__init__.py
spirofs/loader.py
spirofs/engines/__init__.py
spirofs/engines/spiro.py
spirofs/fileserver/__init__.py
spirofs/fileserver/spiro.py
spirofs/runner/__init__.py
spirofs/runner/spam.py
spirofs/runner/spiro.py
spirofs/utils/__init__.py
spirofs/utils/spiro.py
spirofs/utils/spiro_auth.py
spirofs-0.3.dist-info/LICENSE
spirofs-0.3.dist-info/METADATA
spirofs-0.3.dist-info/WHEEL
spirofs-0.3.dist-info/entry_points.txt
spirofs-0.3.dist-info/top_level.txt
spirofs-0.3.dist-info/RECORD
