Metadata-Version: 2.1
Name: spirofs
Version: 0.3
Summary: Salt Fileserver handling dynamic saltenvs and discrete deployments from CI/CD.
Home-page: https://spirostack.com/spirofs/
Author: Jamie Bliss
Author-email: jamie@ivyleav.es
License: UNKNOWN
Project-URL: Bug Reports, https://gitlab.com/spirostack/spirofs/issues
Project-URL: Tip Jar, https://ko-fi.com/astraluma
Project-URL: Source, https://gitlab.com/spirostack/spirofs/
Keywords: salt saltstack spirostack spirofs salt-extension
Platform: UNKNOWN
Classifier: Development Status :: 4 - Beta
Classifier: Intended Audience :: Developers
Classifier: Intended Audience :: System Administrators
Classifier: Environment :: Other Environment
Classifier: Operating System :: OS Independent
Classifier: Topic :: System :: Systems Administration
Classifier: Topic :: System :: Archiving :: Packaging
Classifier: Topic :: Software Development :: Build Tools
Classifier: License :: OSI Approved :: GNU Affero General Public License v3
Classifier: Programming Language :: Python :: 3
Classifier: Programming Language :: Python :: 3.5
Classifier: Programming Language :: Python :: 3.6
Classifier: Programming Language :: Python :: 3.7
Classifier: Programming Language :: Python :: 3.8
Classifier: Programming Language :: Python :: 3.9
Requires-Dist: pymacaroons
